nthcommunity/__init__.py
nthcommunity/nthcommunity.py
nthcommunity-1.0.0.dist-info/LICENSE
nthcommunity-1.0.0.dist-info/METADATA
nthcommunity-1.0.0.dist-info/WHEEL
nthcommunity-1.0.0.dist-info/top_level.txt
nthcommunity-1.0.0.dist-info/RECORD
