Metadata-Version: 2.1
Name: nthcommunity
Version: 1.0.0
Summary: Python API for the nth.community secure data collaboration platform.
Home-page: https://github.com/nthparty/nthcommunity
Author: Nth Party, Ltd.
Author-email: team@nthparty.com
License: MIT
Platform: UNKNOWN
License-File: LICENSE
Requires-Dist: requests (~=2.27)
Requires-Dist: oblivious (~=5.0)
Requires-Dist: bcl (~=2.1)
Requires-Dist: additive (~=0.3)
